al_utils/ActiveLearning.py
al_utils/Sampling.py
al_utils/__init__.py
al_utils/autoaugment.py
al_utils/data.py
al_utils/kcenter_greedy.py
al_utils/partition_data.py
al_utils/power_law.py
al_utils/query_models.py
al_utils/swa_util.py
al_utils/vaal_util.py
al_utils/vae_sampling.py
helper/__init__.py
helper/aml_utils.py
helper/args_util.py
helper/path_extractor.py
helper/subprocess_utils.py
pycls/__init__.py
pycls/core/__init__.py
pycls/core/config.py
pycls/core/losses.py
pycls/core/model_builder.py
pycls/core/optimizer.py
pycls/core/temp.py
pycls/datasets/__init__.py
pycls/datasets/autoaugment.py
pycls/datasets/cifar10.py
pycls/datasets/data.py
pycls/datasets/imagenet.py
pycls/datasets/loader.py
pycls/datasets/paths.py
pycls/datasets/sampler.py
pycls/datasets/transforms.py
pycls/models/__init__.py
pycls/models/anynet.py
pycls/models/coregcn.py
pycls/models/effnet.py
pycls/models/resnet.py
pycls/models/resnet_orig.py
pycls/models/vaal_model.py
pycls/models/resnet_style/__init__.py
pycls/models/resnet_style/resnet.py
pycls/models/resnet_style/resnet_1.py
pycls/models/resnet_style/resnet_2.py
pycls/models/resnet_style/resnet_shake_shake.py
pycls/models/resnet_style/shake_shake_function.py
pycls/models/resnet_style/wide_resnet.py
pycls/models/vgg_style/__init__.py
pycls/models/vgg_style/vgg.py
pycls/models/vgg_style/vgg_1.py
pycls/models/vgg_style/vgg_2.py
pycls/models/vgg_style/vgg_check.py
pycls/models/vgg_style/vgg_mnist.py
pycls/utils/__init__.py
pycls/utils/benchmark.py
pycls/utils/checkpoint.py
pycls/utils/distributed.py
pycls/utils/error_handler.py
pycls/utils/logging.py
pycls/utils/lr_policy.py
pycls/utils/meters.py
pycls/utils/metrics.py
pycls/utils/multiprocessing.py
pycls/utils/net.py
pycls/utils/plotting.py
pycls/utils/timer.py
torchal-0.0.2.dist-info/LICENSE
torchal-0.0.2.dist-info/METADATA
torchal-0.0.2.dist-info/WHEEL
torchal-0.0.2.dist-info/top_level.txt
torchal-0.0.2.dist-info/RECORD
