Metadata-Version: 2.1
Name: torchal
Version: 0.0.2
Summary: A codebase for active learning built on top of pycls.
Home-page: https://github.com/PrateekMunjal/TorchAL
Author: Prateek Munjal
Author-email: prateekmunjal31@gmail.com
License: UNKNOWN
Platform: UNKNOWN
Classifier: Programming Language :: Python :: 3
Classifier: License :: OSI Approved :: MIT License
License-File: LICENSE
Requires-Dist: torch (==1.6.0)
Requires-Dist: torchcontrib (==0.0.2)
Requires-Dist: torchvision (==0.7.0)
Requires-Dist: tqdm (==4.63.0)
Requires-Dist: yacs (==0.1.8)
Requires-Dist: simplejson (==3.17.6)
Requires-Dist: optuna (==2.1.0)
Requires-Dist: plotly (==5.6.0)
Requires-Dist: matplotlib (==3.3.4)
Requires-Dist: scipy (==1.5.2)
Requires-Dist: scikit-learn (==0.24.2)
Requires-Dist: opencv-python (==3.4.2.17)
